spym/__init__.py
spym/_version.py
spym/_accessors/__init__.py
spym/io/__init__.py
spym/io/load.py
spym/io/omicronscala/__init__.py
spym/io/omicronscala/_methods.py
spym/io/omicronscala/_scala.py
spym/io/rhksm4/__init__.py
spym/io/rhksm4/_methods.py
spym/io/rhksm4/_sm4.py
spym/plotting/__init__.py
spym/process/__init__.py
spym/process/filters.py
spym/process/level.py
spym-0.9.2.dist-info/licenses/LICENSE
spym-0.9.2.dist-info/METADATA
spym-0.9.2.dist-info/WHEEL
spym-0.9.2.dist-info/top_level.txt
spym-0.9.2.dist-info/RECORD
