Metadata-Version: 2.4
Name: spym
Version: 0.9.2
Summary: A python package for loading and processing Scanning Probe Microscopy (SPM) data.
Author-email: Mirco Panighel <mirkopanighel@gmail.com>
License-Expression: MIT
Project-URL: Homepage, https://github.com/rescipy-project/spym
Project-URL: Issues, https://github.com/rescipy-project/spym/issues
Classifier: Development Status :: 4 - Beta
Classifier: Intended Audience :: Science/Research
Classifier: Natural Language :: English
Classifier: Programming Language :: Python :: 3
Classifier: Operating System :: OS Independent
Requires-Python: >=3.8
License-File: LICENSE
Dynamic: license-file
